main.py
claude_switcher-0.0.1.dist-info/licenses/LICENSE
claude_switcher-0.0.1.dist-info/METADATA
claude_switcher-0.0.1.dist-info/WHEEL
claude_switcher-0.0.1.dist-info/entry_points.txt
claude_switcher-0.0.1.dist-info/top_level.txt
claude_switcher-0.0.1.dist-info/RECORD
