Metadata-Version: 2.4
Name: claude-switcher
Version: 0.0.1
Summary: Claude模型切换器 - 在不同的Claude模型之间自由切换
License:                                  Apache License
Requires-Python: >=3.11
License-File: LICENSE
Requires-Dist: pyyaml>=6.0
Requires-Dist: requests>=2.28.0
Dynamic: license-file
